openpyxl_style_writer/__init__.py
openpyxl_style_writer/style.py
openpyxl_style_writer/wirter.py
openpyxl_style_writer-1.1.4.dist-info/LICENSE
openpyxl_style_writer-1.1.4.dist-info/METADATA
openpyxl_style_writer-1.1.4.dist-info/WHEEL
openpyxl_style_writer-1.1.4.dist-info/top_level.txt
openpyxl_style_writer-1.1.4.dist-info/RECORD
