Metadata-Version: 2.1
Name: openpyxl_style_writer
Version: 1.1.4
Summary: A wrapper for openpyxl to create and use resualbe style in write only mode
Home-page: https://github.com/Zncl2222/openpyxl_style_writer
Author: Zncl2222
Author-email: zwebapplication@gmail.com
License: MIT
Keywords: openpyxl,excel,style
Classifier: Development Status :: 5 - Production/Stable
Classifier: License :: OSI Approved :: MIT License
Classifier: Programming Language :: Python :: 3
Requires-Python: >=3.6
License-File: LICENSE
Requires-Dist: openpyxl
